xdep/__init__.py
xdep/main.py
xdep-0.1.4.dist-info/licenses/license.txt
xdep-0.1.4.dist-info/METADATA
xdep-0.1.4.dist-info/WHEEL
xdep-0.1.4.dist-info/entry_points.txt
xdep-0.1.4.dist-info/top_level.txt
xdep-0.1.4.dist-info/RECORD
