Metadata-Version: 2.4
Name: xdep
Version: 0.1.4
Summary: An integrated pipeline for developing and evaluating trustworthy computer vision models.
Author-email: Sagar Tamang <sagar.bdr0000@gmail.com>
License-Expression: MIT
Project-URL: Homepage, https://github.com/SAGAR-TAMANG/X-DEP
Project-URL: Repository, https://github.com/SAGAR-TAMANG/X-DEP
Project-URL: Documentation, https://github.com/SAGAR-TAMANG/X-DEP?tab=readme-ov-file#xdep
Project-URL: Issue Tracker, https://github.com/SAGAR-TAMANG/X-DEP/issues
Requires-Python: <3.12,>=3.10
License-File: license.txt
Requires-Dist: lime>=0.2.0.1
Requires-Dist: matplotlib>=3.10.5
Requires-Dist: pillow>=11.3.0
Requires-Dist: rich>=14.1.0
Requires-Dist: scikit-learn>=1.7.1
Requires-Dist: seaborn>=0.13.2
Requires-Dist: tensorflow==2.20.0rc0
Dynamic: license-file
